ostop/__init__.py
ostop/linux.py
ostop/mac.py
ostop/main.py
ostop/windows.py
ostop-1.5.dist-info/entry_points.txt
ostop-1.5.dist-info/LICENSE
ostop-1.5.dist-info/WHEEL
ostop-1.5.dist-info/METADATA
ostop-1.5.dist-info/RECORD
