Metadata-Version: 2.1
Name: ostop
Version: 1.5
Summary: Cross-Compatible Python implementation of top command.
Home-page: https://github.com/burgess01/top
License: MIT
Author: Katherine Burgess
Author-email: 20burgessk@gmail.com
Requires-Python: >=3.7.2,<4.0.0
Classifier: License :: OSI Approved :: MIT License
Classifier: Programming Language :: Python :: 3
Classifier: Programming Language :: Python :: 3.8
Classifier: Programming Language :: Python :: 3.9
Classifier: Programming Language :: Python :: 3.10
Classifier: Programming Language :: Python :: 3.11
Requires-Dist: datetime (>=4.7,<5.0)
Requires-Dist: hurry-filesize (>=0.9,<0.10)
Requires-Dist: psutil (>=5.9.3,<6.0.0)
Project-URL: Repository, https://github.com/burgess01/top
